Metadata-Version: 2.1
Name: tkvlc
Version: 1.0.0
Summary: A Minimal python-vlc Tkinter Helper Library
Home-page: https://gitlab.com/SafwanLjd/PyTkinterVLC
Download-URL: https://gitlab.com/SafwanLjd/PyTkinterVLC/-/archive/1.0.0/PyTkinterVLC-1.0.0.tar.gz
Author: Safwan Ljd
Classifier: Development Status :: 5 - Production/Stable
Classifier: Intended Audience :: Developers
Classifier: Topic :: Software Development :: Build Tools
Classifier: License :: OSI Approved :: GNU General Public License v3 (GPLv3)
Classifier: Natural Language :: English
Classifier: Programming Language :: Python :: 3
License-File: LICENSE
